tf_restore_helper/__init__.py
tf_restore_helper/__main__.py
tf_restore_helper/py.typed
tf_restore_helper/tf_restore_helper.py
tf_restore_helper-0.1.1.dist-info/entry_points.txt
tf_restore_helper-0.1.1.dist-info/LICENSE.rst
tf_restore_helper-0.1.1.dist-info/WHEEL
tf_restore_helper-0.1.1.dist-info/METADATA
tf_restore_helper-0.1.1.dist-info/RECORD
