Metadata-Version: 2.1
Name: tf-restore-helper
Version: 0.1.1
Summary: Tf Restore Helper
Home-page: https://github.com/dogfish182/tf-restore-helper
License: MIT
Author: Gary Hawker
Author-email: dogfish@gmail.com
Requires-Python: >=3.7.0,<4.0.0
Classifier: License :: OSI Approved :: MIT License
Classifier: Programming Language :: Python :: 3
Classifier: Programming Language :: Python :: 3.10
Classifier: Programming Language :: Python :: 3.6
Classifier: Programming Language :: Python :: 3.7
Classifier: Programming Language :: Python :: 3.8
Classifier: Programming Language :: Python :: 3.9
Requires-Dist: boto3 (>=1.17,<1.21)
Requires-Dist: click (>=7,<9)
Requires-Dist: click-logging (>=1.0,<1.1)
Requires-Dist: coloredlogs (>=15.0,<15.1)
Requires-Dist: flatplan (>=1.3,<1.4)
Project-URL: Changelog, https://github.com/dogfish182/tf-restore-helper/releases
Project-URL: Documentation, https://tf-restore-helper.readthedocs.io
Project-URL: Repository, https://github.com/dogfish182/tf-restore-helper
